{
  "report_metadata": {
    "date": "2025-08-22",
    "data_date": "2025-08-21",
    "site": "Nchwaning 3",
    "engineer": "Sello Sease",
    "timestamp": "07:46",
    "report_type": "Daily Report"
  },
  "safety": {
    "status": "clear",
    "incidents": 0,
    "details": []
  },
  "production": {
    "rom": {"actual": 6319, "target": 8060, "variance": -1741, "variance_percentage": 78.40, "unit": "tonnes"},
    "decline": {"actual": 5348, "target": 7498, "variance": -2150, "variance_percentage": 71.32, "unit": "tonnes"},
    "product": {"actual": 5698, "target": 6618, "variance": -920, "variance_percentage": 86.10, "unit": "tonnes"},
    "loads": [
      {"shift": "day", "load_number": 1, "truckloads_tipped": 79, "target": null},
      {"shift": "afternoon", "load_number": 2, "truckloads_tipped": 88, "target": null},
      {"shift": "night", "load_number": 3, "truckloads_tipped": 66, "target": null}
    ],
    "blast": {"faces": null, "breakdown": null, "note": "12Mn & 1Waste"}
  },
  "equipment_availability": {
    "tmm": {"DT": 72, "FL": 98, "HD": 67, "RT": 76, "SR": 55},
    "specialized": [
      {"code": "UV", "availability": 78},
      {"code": "GD11", "availability": 100},
      {"code": "DZ11", "availability": 0},
      {"code": "UV044", "availability": 67}
    ]
  },
  "shift_readiness": {
    "production_tmm": {
      "DT": {"available": 11, "total": 14},
      "FL": {"available": 10, "total": 10},
      "HD": {"available": 5, "total": 9},
      "RT": {"available": 9, "total": 10},
      "SR": {"available": 4, "total": 9}
    }
  },
  "breakdowns": {
    "current_breakdowns": [
      {"unit": "DT 0171", "issue": "Hyd oil leak ,spares"},
      {"unit": "HD0050", "issue": "Slip ring motor"},
      {"unit": "HD0054", "issue": "Fire incident"},
      {"unit": "HD 0062", "issue": "Drifters"},
      {"unit": "RT0054", "issue": "Carousel bent"},
      {"unit": "SR 0024", "issue": "Boom"},
      {"unit": "SR 0030", "issue": "Damage"},
      {"unit": "SR 0038", "issue": "engine Smoking"},
      {"unit": "UV 0045", "issue": "Not starting"},
      {"unit": "UV 0047", "issue": "Brakes release (Spares)"},
      {"unit": "DZ 0011", "issue": "Drive line"}
    ]
  },
  "operational": {
    "main_fans": null,
    "plant_blockages": 0,
    "fire_alarms": 0
  },
  "source_validation": {
    "safety_status": {"value": "All clear", "source_line": "207", "source_quote": "- All clear", "confidence": "HIGH"},
    "rom_actual": {"value": 6319, "source_line": "209", "source_quote": "6319 vs 8060", "confidence": "HIGH"},
    "rom_target": {"value": 8060, "source_line": "209", "source_quote": "6319 vs 8060", "confidence": "HIGH"},
    "decline_actual": {"value": 5348, "source_line": "212", "source_quote": "5348 vs 7498", "confidence": "HIGH"},
    "decline_target": {"value": 7498, "source_line": "212", "source_quote": "5348 vs 7498", "confidence": "HIGH"},
    "product_actual": {"value": 5698, "source_line": "215", "source_quote": "5698 vs 6618", "confidence": "HIGH"},
    "product_target": {"value": 6618, "source_line": "215", "source_quote": "5698 vs 6618", "confidence": "HIGH"},
    "loads_day": {"value": 79, "source_line": "218", "source_quote": "79, 88 & 66", "confidence": "HIGH"},
    "loads_afternoon": {"value": 88, "source_line": "218", "source_quote": "79, 88 & 66", "confidence": "HIGH"},
    "loads_night": {"value": 66, "source_line": "218", "source_quote": "79, 88 & 66", "confidence": "HIGH"},
    "blast_note": {"value": "12Mn & 1Waste", "source_line": "221", "source_quote": "12Mn & 1Waste", "confidence": "HIGH"},
    "hds_availability": {"value": 67, "source_line": "224", "source_quote": "HDs: 67", "confidence": "HIGH"},
    "dts_availability": {"value": 72, "source_line": "225", "source_quote": "DTs: 72", "confidence": "HIGH"},
    "fls_availability": {"value": 98, "source_line": "226", "source_quote": "FLs: 98", "confidence": "HIGH"},
    "rts_availability": {"value": 76, "source_line": "227", "source_quote": "RTs: 76", "confidence": "HIGH"},
    "srs_availability": {"value": 55, "source_line": "228", "source_quote": "SRs: 55", "confidence": "HIGH"},
    "uvs_availability": {"value": 78, "source_line": "229", "source_quote": "UVs: 78", "confidence": "HIGH"},
    "gd11_availability": {"value": 100, "source_line": "231", "source_quote": "GD11: 100", "confidence": "HIGH"},
    "dz11_availability": {"value": 0, "source_line": "232", "source_quote": "DZ11: 0", "confidence": "HIGH"},
    "uv044_availability": {"value": 67, "source_line": "233", "source_quote": "UV044: 67", "confidence": "HIGH"},
    "hds_sos_available": {"value": 5, "source_line": "236", "source_quote": "HDs: 5/9", "confidence": "HIGH"},
    "hds_sos_total": {"value": 9, "source_line": "236", "source_quote": "HDs: 5/9", "confidence": "HIGH"},
    "dts_sos_available": {"value": 11, "source_line": "237", "source_quote": "DTs: 11/14", "confidence": "HIGH"},
    "dts_sos_total": {"value": 14, "source_line": "237", "source_quote": "DTs: 11/14", "confidence": "HIGH"},
    "fls_sos_available": {"value": 10, "source_line": "238", "source_quote": "FLs: 10/10", "confidence": "HIGH"},
    "fls_sos_total": {"value": 10, "source_line": "238", "source_quote": "FLs: 10/10", "confidence": "HIGH"},
    "rts_sos_available": {"value": 9, "source_line": "239", "source_quote": "RTs: 9/10", "confidence": "HIGH"},
    "rts_sos_total": {"value": 10, "source_line": "239", "source_quote": "RTs: 9/10", "confidence": "HIGH"},
    "srs_sos_available": {"value": 4, "source_line": "240", "source_quote": "SRs: 4/9", "confidence": "HIGH"},
    "srs_sos_total": {"value": 9, "source_line": "240", "source_quote": "SRs: 4/9", "confidence": "HIGH"},
    "uvs_sos_available": {"value": 7, "source_line": "241", "source_quote": "UVs: 7/9", "confidence": "HIGH"},
    "uvs_sos_total": {"value": 9, "source_line": "241", "source_quote": "UVs: 7/9", "confidence": "HIGH"},
    "manlifts_available": {"value": 3, "source_line": "243", "source_quote": "Manlifts:3/4", "confidence": "HIGH"},
    "manlifts_total": {"value": 4, "source_line": "243", "source_quote": "Manlifts:3/4", "confidence": "HIGH"},
    "emulsion_uv_available": {"value": 3, "source_line": "245", "source_quote": "Emulsion UV: 3/4", "confidence": "HIGH"},
    "emulsion_uv_total": {"value": 4, "source_line": "245", "source_quote": "Emulsion UV: 3/4", "confidence": "HIGH"},
    "fire_alarms": {"value": 0, "source_line": "260", "source_quote": "- No alarms", "confidence": "HIGH"},
    "plant_blockages": {"value": 0, "source_line": "266", "source_quote": "- Al clear", "confidence": "HIGH"}
  }
}