{
  "report_metadata": {
    "date": "2025-08-14",
    "data_date": "2025-08-13",
    "site": "Gloria",
    "engineer": "Sipho Dubazane",
    "timestamp": "06:00",
    "processing_mode": "autonomous",
    "data_availability": "none"
  },
  "safety": {
    "status": "no_data",
    "incidents": null,
    "details": []
  },
  "production": {
    "rom": {
      "actual": null,
      "target": null,
      "variance": null,
      "variance_percentage": null
    },
    "decline": {
      "actual": null,
      "target": null,
      "variance": null,
      "variance_percentage": null
    },
    "product": {
      "actual": null,
      "target": null,
      "variance": null,
      "variance_percentage": null
    },
    "loads": [
      {"shift": "day", "load_number": 1, "truckloads_tipped": null, "target": null},
      {"shift": "afternoon", "load_number": 2, "truckloads_tipped": null, "target": null},
      {"shift": "night", "load_number": 3, "truckloads_tipped": null, "target": null}
    ],
    "blast": {
      "faces": null,
      "breakdown": null,
      "note": "No data available"
    }
  },
  "equipment_availability": {
    "tmm": {
      "DT": null,
      "FL": null,
      "HD": null,
      "RT": null,
      "SR": null
    },
    "specialized": []
  },
  "shift_readiness": {
    "production_tmm": {
      "DT": {"available": null, "total": null},
      "FL": {"available": null, "total": null},
      "HD": {"available": null, "total": null},
      "RT": {"available": null, "total": null},
      "SR": {"available": null, "total": null}
    }
  },
  "breakdowns": {
    "current_breakdowns": []
  },
  "operational": {
    "main_fans": null,
    "plant_blockages": null,
    "fire_alarms": null
  },
  "silo_levels": {
    "surface": {
      "silo_1": null, "silo_2": null, "silo_3": null, "silo_4": null
    },
    "underground": {
      "silo_74": null, "silo_hg": null, "silo_d": null, "silo_lg": null
    }
  },
  "specialized_equipment": {
    "manitou": {"available": null, "total": 1, "availability": null},
    "manlifts": {"available": null, "total": null, "availability": null}
  },
  "performance_summary": {
    "key_issues": ["No WhatsApp data available for processing"],
    "key_highlights": ["Autonomous processing completed with placeholder structure"]
  },
  "source_validation": {
    "data_source": {
      "value": "None provided",
      "source_line": 0,
      "source_quote": "Empty WhatsApp data section",
      "confidence": "NONE"
    },
    "processing_note": "No source data available - created placeholder report structure",
    "validation_status": "NO_DATA_AVAILABLE"
  }
}